chronograph/__init__.py
chronograph/admin.py
chronograph/models.py
chronograph/settings.py
chronograph/views.py
chronograph/compatibility/__init__.py
chronograph/compatibility/dates.py
chronograph/fixtures/test_jobs.json
chronograph/management/__init__.py
chronograph/management/commands/__init__.py
chronograph/management/commands/cron.py
chronograph/management/commands/cron_clean.py
chronograph/management/commands/cron_serial.py
chronograph/management/commands/cronserver.py
chronograph/management/commands/run_job.py
chronograph/templates/chronograph/error_message.txt
chronograph/templatetags/__init__.py
chronograph/templatetags/chronograph_tags.py
chronograph/tests/__init__.py
chronograph/tests/commands.py
django_chronograph_ispm-0.0.3.data/scripts/chronograph
django_chronograph_ispm-0.0.3.dist-info/DESCRIPTION.rst
django_chronograph_ispm-0.0.3.dist-info/METADATA
django_chronograph_ispm-0.0.3.dist-info/RECORD
django_chronograph_ispm-0.0.3.dist-info/WHEEL
django_chronograph_ispm-0.0.3.dist-info/dependency_links.txt
django_chronograph_ispm-0.0.3.dist-info/metadata.json
django_chronograph_ispm-0.0.3.dist-info/top_level.txt
