Metadata-Version: 2.0
Name: django-chronograph-ispm
Version: 0.0.3
Summary: Django iChronograph ISPM customized
Home-page: https://github.com/ISPM/ispm-django-chronograph
Author: ISPM
Author-email: dev@ispm.com
License: BSD
Keywords: cron django-chronograph
Platform: UNKNOWN
Classifier: Environment :: Web Environment
Classifier: Intended Audience :: Developers
Classifier: License :: OSI Approved :: BSD License
Classifier: Operating System :: OS Independent
Classifier: Programming Language :: Python
Classifier: Framework :: Django
Provides-Extra: DateUtil
Requires-Dist: python-dateutil (<=1.5); extra == 'DateUtil'
Provides-Extra: Django
Requires-Dist: Django (>=1.5); extra == 'Django'
